google/cloud/kms_inventory/__init__.py
google/cloud/kms_inventory/gapic_version.py
google/cloud/kms_inventory/py.typed
google/cloud/kms_inventory_v1/__init__.py
google/cloud/kms_inventory_v1/gapic_metadata.json
google/cloud/kms_inventory_v1/gapic_version.py
google/cloud/kms_inventory_v1/py.typed
google/cloud/kms_inventory_v1/services/__init__.py
google/cloud/kms_inventory_v1/services/key_dashboard_service/__init__.py
google/cloud/kms_inventory_v1/services/key_dashboard_service/async_client.py
google/cloud/kms_inventory_v1/services/key_dashboard_service/client.py
google/cloud/kms_inventory_v1/services/key_dashboard_service/pagers.py
google/cloud/kms_inventory_v1/services/key_dashboard_service/transports/__init__.py
google/cloud/kms_inventory_v1/services/key_dashboard_service/transports/base.py
google/cloud/kms_inventory_v1/services/key_dashboard_service/transports/grpc.py
google/cloud/kms_inventory_v1/services/key_dashboard_service/transports/grpc_asyncio.py
google/cloud/kms_inventory_v1/services/key_dashboard_service/transports/rest.py
google/cloud/kms_inventory_v1/services/key_dashboard_service/transports/rest_base.py
google/cloud/kms_inventory_v1/services/key_tracking_service/__init__.py
google/cloud/kms_inventory_v1/services/key_tracking_service/async_client.py
google/cloud/kms_inventory_v1/services/key_tracking_service/client.py
google/cloud/kms_inventory_v1/services/key_tracking_service/pagers.py
google/cloud/kms_inventory_v1/services/key_tracking_service/transports/__init__.py
google/cloud/kms_inventory_v1/services/key_tracking_service/transports/base.py
google/cloud/kms_inventory_v1/services/key_tracking_service/transports/grpc.py
google/cloud/kms_inventory_v1/services/key_tracking_service/transports/grpc_asyncio.py
google/cloud/kms_inventory_v1/services/key_tracking_service/transports/rest.py
google/cloud/kms_inventory_v1/services/key_tracking_service/transports/rest_base.py
google/cloud/kms_inventory_v1/types/__init__.py
google_cloud_kms_inventory-0.3.0.dist-info/licenses/LICENSE
google_cloud_kms_inventory-0.3.0.dist-info/METADATA
google_cloud_kms_inventory-0.3.0.dist-info/WHEEL
google_cloud_kms_inventory-0.3.0.dist-info/top_level.txt
google_cloud_kms_inventory-0.3.0.dist-info/RECORD
